memeda/__init__.py
memeda-0.0.4.dist-info/DESCRIPTION.rst
memeda-0.0.4.dist-info/METADATA
memeda-0.0.4.dist-info/RECORD
memeda-0.0.4.dist-info/WHEEL
memeda-0.0.4.dist-info/entry_points.txt
memeda-0.0.4.dist-info/metadata.json
memeda-0.0.4.dist-info/top_level.txt
