Metadata-Version: 2.0
Name: memeda
Version: 0.0.4
Summary: 么么哒
Home-page: UNKNOWN
Author: physics
Author-email: jihu9@163.com
License: UNKNOWN
Platform: UNKNOWN
